deckcam/__init__.py
deckcam/__main__.py
deckcam/main.py
deckcam-0.1.0.dist-info/WHEEL
deckcam-0.1.0.dist-info/METADATA
deckcam-0.1.0.dist-info/RECORD
